Metadata-Version: 2.1
Name: lilfilter
Version: 0.0.1
Summary: Utilities for filtering and resampling signals
Home-page: https://github.com/danpovey/filtering
Author: Daniel Povey
Author-email: dpovey@gmail.com
License: UNKNOWN
Keywords: resampling,audio
Platform: UNKNOWN
Classifier: Development Status :: 3 - Alpha
Classifier: Programming Language :: Python :: 3
Classifier: Topic :: Utilities
Classifier: Operating System :: OS Independent
Requires-Python: >=3.5
